{"cameraMode":{"drawMode":0,"name":"Shaded","section":"Shading Mode"},"sceneLighting":true,"audioPlay":false,"sceneViewState":{"m_AlwaysRefresh":false,"showFog":true,"showSkybox":true,"showFlares":true,"showImageEffects":true,"showParticleSystems":true,"showVisualEffectGraphs":true,"m_FxEnabled":true},"in2DMode":false,"pivot":{"x":0.2596473693847656,"y":-1.8567428588867188,"z":-2.817089080810547},"rotation":{"x":0.10864292085170746,"y":-0.8220847845077515,"z":0.1675007939338684,"w":0.5332130193710327},"size":8.573148727416993,"orthographic":false}